thinking_machine/__init__.py
thinking_machine-0.0.1.dist-info/LICENSE
thinking_machine-0.0.1.dist-info/METADATA
thinking_machine-0.0.1.dist-info/WHEEL
thinking_machine-0.0.1.dist-info/top_level.txt
thinking_machine-0.0.1.dist-info/RECORD
